composer_tools/__init__.py
composer_tools/converters/__init__.py
composer_tools/converters/short_codes.py
composer_tools/converters/tests/__init__.py
composer_tools/converters/tests/test_short_codes.py
composer_tools-0.1.4.dist-info/licenses/LICENSE
composer_tools-0.1.4.dist-info/METADATA
composer_tools-0.1.4.dist-info/WHEEL
composer_tools-0.1.4.dist-info/top_level.txt
composer_tools-0.1.4.dist-info/RECORD
