Metadata-Version: 2.4
Name: composer-tools
Version: 0.1.4
Summary: A bunch of useful tools for creating trading strategies with Composer.trade
Requires-Python: >=3.11
License-File: LICENSE
Dynamic: license-file
